omeka_s_tools/__init__.py
omeka_s_tools/_nbdev.py
omeka_s_tools/api.py
omeka_s_tools-0.3.0.dist-info/LICENSE
omeka_s_tools-0.3.0.dist-info/METADATA
omeka_s_tools-0.3.0.dist-info/WHEEL
omeka_s_tools-0.3.0.dist-info/entry_points.txt
omeka_s_tools-0.3.0.dist-info/top_level.txt
omeka_s_tools-0.3.0.dist-info/RECORD
