Metadata-Version: 2.1
Name: omeka-s-tools
Version: 0.3.0
Summary: Tools for working with Omeka S API
Home-page: https://github.com/wragge/omeka_s_tools/tree/master/
Author: Tim Sherratt
Author-email: tim@timsherratt.org
License: MIT License
Keywords: Omeka
Platform: UNKNOWN
Classifier: Development Status :: 4 - Beta
Classifier: Intended Audience :: Developers
Classifier: Natural Language :: English
Classifier: Programming Language :: Python :: 3.8
Classifier: License :: OSI Approved :: MIT License
Requires-Python: >=3.8
Requires-Dist: pip
Requires-Dist: packaging
Requires-Dist: requests
Requires-Dist: requests-cache
Provides-Extra: dev
